langchain_tableau/__init__.py
langchain_tableau/license_file.txt
langchain_tableau/tools/__init__.py
langchain_tableau/tools/prompts.py
langchain_tableau/tools/simple_datasource_qa.py
langchain_tableau/utilities/__init__.py
langchain_tableau/utilities/auth.py
langchain_tableau/utilities/metadata.py
langchain_tableau/utilities/models.py
langchain_tableau/utilities/simple_datasource_qa.py
langchain_tableau/utilities/utils.py
langchain_tableau/utilities/vizql_data_service.py
langchain_tableau-0.4.39.dist-info/METADATA
langchain_tableau-0.4.39.dist-info/WHEEL
langchain_tableau-0.4.39.dist-info/RECORD
